avbv/__init__.py
avbv/avbv.py
avbv_converter-1.0.0.dist-info/LICENSE
avbv_converter-1.0.0.dist-info/METADATA
avbv_converter-1.0.0.dist-info/WHEEL
avbv_converter-1.0.0.dist-info/top_level.txt
avbv_converter-1.0.0.dist-info/RECORD
