Metadata-Version: 2.1
Name: avbv-converter
Version: 1.0.0
Summary: a simple av bv converter
Home-page: https://github.com/xiaohuangren1001/Bilibili-av-bv-converter
Author: lenovo
Author-email: 2276316223@qq.com
License: UNKNOWN
Platform: UNKNOWN
